add_prompt/__init__.py
add_prompt-0.0.1.dist-info/METADATA
add_prompt-0.0.1.dist-info/WHEEL
add_prompt-0.0.1.dist-info/RECORD
