Metadata-Version: 2.4
Name: add-prompt
Version: 0.0.1
Summary: CLI tool for adding Claude Code prompts from GitHub. Coming soon.
Project-URL: Repository, https://github.com/kasperjunge/agent-resources
License-Expression: MIT
Keywords: agent,ai,claude,claude-code,prompt
Requires-Python: >=3.10
